tomlrun/__init__.py
tomlrun/_version.py
tomlrun/cli.py
tomlrun/py.typed
tomlrun/utils.py
toml_run-0.0.2.dist-info/METADATA
toml_run-0.0.2.dist-info/WHEEL
toml_run-0.0.2.dist-info/entry_points.txt
toml_run-0.0.2.dist-info/licenses/LICENSE
toml_run-0.0.2.dist-info/RECORD
