Metadata-Version: 2.4
Name: toml-run
Version: 0.0.2
Summary: Define custom scripts in your pyproject.toml and easily run them with this dependency free tool.
Project-URL: Changelog, https://github.com/cssnr/toml-run/releases
Project-URL: Discord, https://discord.gg/wXy6m2X8wY
Project-URL: Documentation, https://cssnr.github.io/toml-run/
Project-URL: Funding, https://ko-fi.com/cssnr
Project-URL: GitHub, https://github.com/cssnr/toml-run
Project-URL: Homepage, https://cssnr.com/
Project-URL: Issues, https://github.com/cssnr/toml-run/issues
Author: Shane
License: MIT License
License-File: LICENSE
Classifier: Natural Language :: English
Classifier: Operating System :: OS Independent
Classifier: Programming Language :: Python
Classifier: Programming Language :: Python :: 3
Classifier: Programming Language :: Python :: 3 :: Only
Classifier: Typing :: Typed
Requires-Python: >=3.8
Requires-Dist: tomli>=1.1.0; python_version < '3.11'
